appabuild/__init__.py
appabuild/exceptions.py
appabuild/logger.py
appabuild/setup.py
appabuild/cli/__init__.py
appabuild/cli/database.py
appabuild/cli/lca.py
appabuild/cli/main.py
appabuild/config/__init__.py
appabuild/config/appa_lca.py
appabuild/config/lca.py
appabuild/database/__init__.py
appabuild/database/bw_databases.py
appabuild/database/databases.py
appabuild/database/serialized_data.py
appabuild/database/user_database_elements.py
appabuild/database/generator/__init__.py
appabuild/database/generator/eime.py
appabuild/model/__init__.py
appabuild/model/builder.py
appabuild/model/graph.py
appabuild/output/__init__.py
appabuild-0.4.0.dist-info/METADATA
appabuild-0.4.0.dist-info/WHEEL
appabuild-0.4.0.dist-info/entry_points.txt
appabuild-0.4.0.dist-info/licenses/LICENSE.md
appabuild-0.4.0.dist-info/RECORD
