Metadata-Version: 2.4
Name: appabuild
Version: 0.4.0
Summary: Appa Build is a package to build impact models
Project-URL: Source, https://github.com/appalca/appabuild/
Author-email: Maxime Peralta <maxime.peralta@cea.fr>
Maintainer-email: Maxime Peralta <maxime.peralta@cea.fr>
License: # GNU LESSER GENERAL PUBLIC LICENSE
License-File: LICENSE.md
Keywords: ecodesign,life cycle assessment
Classifier: Intended Audience :: Developers
Classifier: Intended Audience :: Manufacturing
Classifier: Intended Audience :: Science/Research
Classifier: Programming Language :: Python
Classifier: Programming Language :: Python :: 3
Classifier: Topic :: Scientific/Engineering
Requires-Python: <3.12,>=3.11
Requires-Dist: aenum
Requires-Dist: apparun==0.4.0
Requires-Dist: brightway25==1.1.0
Requires-Dist: bw-migrations==0.2
Requires-Dist: bw-processing==1.0
Requires-Dist: bw-simapro-csv==0.4.3
Requires-Dist: bw2analyzer==0.11.8
Requires-Dist: bw2calc==2.2.1
Requires-Dist: bw2data==4.5.1
Requires-Dist: bw2io==0.9.11
Requires-Dist: bw2parameters==1.1.0
Requires-Dist: click<=8.1.8
Requires-Dist: fastapi
Requires-Dist: ipython<=8.34.0,>=7.6.0
Requires-Dist: kaleido
Requires-Dist: lca-algebraic-bw25==1.3.1
Requires-Dist: matplotlib
Requires-Dist: mermaid-py==0.7.1
Requires-Dist: numpy==1.26.4
Requires-Dist: omegaconf
Requires-Dist: pandas==2.3.3
Requires-Dist: plotly
Requires-Dist: pyarrow==22.0.0
Requires-Dist: pydantic
Requires-Dist: ruamel-yaml
Requires-Dist: scipy
Requires-Dist: seaborn
Requires-Dist: tqdm
Requires-Dist: typer==0.15.1
Requires-Dist: uvicorn[standard]
